[
  {
    "src": "/images/imagesInspiration/Eclaircie15.webp",
    "alt": "Vue panoramique sur un jardin paysager luxuriant, mettant en avant des cyprès, des palmiers et des collines en arrière-plan."
  },
  {
    "src": "/images/imagesInspiration/Eclaircie16.webp",
    "alt": "Terrasse extérieure moderne avec des meubles en bois, entourée de verdure luxuriante et d'arbres majestueux."
  },
  {
    "src": "/images/imagesInspiration/Eclaircie17.webp",
    "alt": "Jardinier utilisant un souffleur pour nettoyer les feuilles près d'une piscine, avec des plantes bien entretenues et la mer en arrière-plan."
  },
  {
    "src": "/images/imagesInspiration/Eclaircie18.webp",
    "alt": "Homme en train de repositionner un pot de fleurs en terre cuite dans un jardin bien aménagé."
  },
  {
    "src": "/images/imagesInspiration/Eclaircie19.webp",
    "alt": "Jardin minimaliste avec des cactus et des plantes succulentes alignés le long d'une clôture en bois."
  },
  {
    "src": "/images/imagesInspiration/Eclaircie20.webp",
    "alt": "Gros plan sur des plantes grasses avec une pelouse impeccable et une piscine en arrière-plan."
  },
  {
    "src": "/images/imagesInspiration/Eclaircie21.webp",
    "alt": "Mains d'un jardinier travaillant sur des plantations, entourées de fleurs et de végétation."
  }
]
